SPIQuadCopter/spiSlave/spi_slave.sv
module spi_slave #(
    parameter DATA_WIDTH = 8
)(
    input  logic                   i_clk,
    input  logic                   i_rst,
    
    // SPI Physical Interface
    input  logic                   i_sclk,
    input  logic                   i_cs_n,
    input  logic                   i_mosi,
    output logic                   o_miso,
    
    // User / System Interface
    input  logic [DATA_WIDTH-1:0]  i_tx_data,  // Data to send
    input  logic                   i_tx_valid, // Pulse high to load data
    output logic                   o_tx_ready, // High = Safe to load new data
    output logic                   o_busy,     // High = SPI transaction in progress
    
    output logic [DATA_WIDTH-1:0]  o_rx_data,  // Received data
    output logic                   o_data_valid, // High = New rx_data available
    output logic                   o_cs_n_sync   // Synchronized CS_n output
);

    // --- 1. Synchronization & Edge Detection ---
    logic [2:0] sclk_sync;
    logic [2:0] cs_n_sync;
    logic [1:0] mosi_sync;

    always_ff @(posedge i_clk or posedge i_rst) begin
        if (i_rst) begin
            sclk_sync <= 3'b000;
            cs_n_sync <= 3'b111;
            mosi_sync <= 2'b00;
        end else begin
            sclk_sync <= {sclk_sync[1:0], i_sclk};
            cs_n_sync <= {cs_n_sync[1:0], i_cs_n};
            mosi_sync <= {mosi_sync[0], i_mosi};
        end
    end

    // Derived signals from synchronizers
    wire sclk_rising  = (sclk_sync[2:1] == 2'b01);
    wire sclk_falling = (sclk_sync[2:1] == 2'b10);
    wire cs_active    = ~cs_n_sync[1]; // Active Low CS
    
    // Output the Busy status immediately based on synchronized CS
    assign o_busy = cs_active;
    assign o_cs_n_sync = cs_n_sync[1];

    // --- 2. Data Path & Logic ---
    logic [$clog2(DATA_WIDTH)-1:0] bit_cnt;
    logic [DATA_WIDTH-1:0] rx_shift_reg;
    logic [DATA_WIDTH-1:0] tx_shift_reg;
    logic [DATA_WIDTH-1:0] tx_holding_reg; 

    always_ff @(posedge i_clk or posedge i_rst) begin
        if (i_rst) begin
            bit_cnt        <= DATA_WIDTH - 1;
            o_rx_data      <= '0;
            o_data_valid   <= 1'b0;
            rx_shift_reg   <= '0;
            tx_shift_reg   <= '0;
            tx_holding_reg <= '0;
            o_tx_ready     <= 1'b1;
        end else begin
            o_data_valid <= 1'b0;

            // --- A. User Interface Logic (Safe Loading) ---
            if (i_tx_valid && o_tx_ready) begin
                tx_holding_reg <= i_tx_data;
                o_tx_ready     <= 1'b0; // Lock buffer until SPI takes it
            end

            // --- B. SPI Transaction Logic ---
            if (!cs_active) begin
                // IDLE STATE
                bit_cnt <= DATA_WIDTH - 1; 
                
                // If the user loaded data, move it to the shifter immediately
                if (o_tx_ready == 1'b0) begin
                    tx_shift_reg <= tx_holding_reg;
                    o_tx_ready   <= 1'b1; // Unlock buffer
                end
            end 
            else begin
                // ACTIVE STATE (Busy)
                
                // Sample MOSI (Rising Edge)
                if (sclk_rising) begin
                    rx_shift_reg <= {rx_shift_reg[DATA_WIDTH-2:0], mosi_sync[1]};
                    if (bit_cnt == 0) begin
                        o_rx_data    <= {rx_shift_reg[DATA_WIDTH-2:0], mosi_sync[1]};
                        o_data_valid <= 1'b1;
                    end
                end

                // Shift MISO (Falling Edge)
                if (sclk_falling) begin
                    if (bit_cnt > 0) begin
                        bit_cnt      <= bit_cnt - 1;
                        tx_shift_reg <= {tx_shift_reg[DATA_WIDTH-2:0], 1'b0};
                    end else begin
                        // Byte complete. Prepare for next byte in stream (if any).
                        bit_cnt <= DATA_WIDTH - 1;
                        
                        // Check if user provided new data in holding register
                        if (o_tx_ready == 1'b0) begin
                            tx_shift_reg <= tx_holding_reg;
                            o_tx_ready   <= 1'b1; // Unlock buffer
                        end else begin
                            tx_shift_reg <= '0; // Underflow: Send Zeros
                        end
                    end
                end
            end
        end
    end

    // Tri-state MISO
    assign o_miso = (cs_active) ? tx_shift_reg[DATA_WIDTH-1] : 1'bZ;

endmodule // SPI_Slave

SPIQuadCopter/spiSlave/spi_slave_tb.sv
/**
 * SPI Slave Testbench (Self-Checking)
 * 
 * Tests the SPI Slave module in Mode 0 operation with randomized data.
 */

`timescale 1ns/1ps

module spi_slave_tb;

    // Parameters
    parameter DATA_WIDTH = 8;
    parameter CLK_PERIOD = 10;     // 100 MHz System Clock
    parameter SCLK_PERIOD = 50;    // 20 MHz SPI Clock (1/5 System Clock)

    // System Signals
    logic clk = 0;
    logic rst = 1;
    
    // SPI Signals (Master Output)
    logic sclk = 0;
    logic cs_n = 1;
    logic mosi = 0;
    
    // SPI Signal (Slave Output)
    wire  miso;
    
    // User Interface Signals (Slave Side)
    logic [DATA_WIDTH-1:0] tx_data_in; 
    logic tx_valid = 0;
    wire  tx_ready;
    wire  busy;
    wire  [DATA_WIDTH-1:0] rx_data;
    wire  rx_valid;

    // Verification Variables
    int error_count = 0;

    // Instantiate DUT
    // Instantiate DUT
    spi_slave #(.DATA_WIDTH(DATA_WIDTH)) dut (
        .i_clk(clk),
        .i_rst(rst),
        .i_sclk(sclk),
        .i_cs_n(cs_n),
        .i_mosi(mosi),
        .o_miso(miso),
        .i_tx_data(tx_data_in),
        .i_tx_valid(tx_valid),
        .o_tx_ready(tx_ready),
        .o_busy(busy),
        .o_rx_data(rx_data),
        .o_data_valid(rx_valid)
    );

    // System Clock Generation
    always #(CLK_PERIOD/2) clk = ~clk;

    // SPI Master Task (Mode 0: CPOL=0, CPHA=0)
    // Returns the byte received from Slave (MISO)
    task automatic spi_transfer(
        input  logic [DATA_WIDTH-1:0] tx_byte,
        output logic [DATA_WIDTH-1:0] rx_byte
    );
        integer i;
        begin
            rx_byte = 0;
            cs_n = 0; // Assert CS
            #(SCLK_PERIOD); // Setup time
            
            for (i = DATA_WIDTH-1; i >= 0; i--) begin
                mosi = tx_byte[i]; // Master drives MOSI
                
                #(SCLK_PERIOD/2) sclk = 1; // Rising edge (Slave samples MOSI)
                
                // Sample MISO on Rising Edge (Mode 0) or slightly after
                // We sample just before falling edge to be safe in simulation
                rx_byte[i] = miso; 
                
                #(SCLK_PERIOD/2) sclk = 0; // Falling edge (Slave shifts MISO)
            end
            
            #(SCLK_PERIOD/2);
            cs_n = 1; // De-assert CS
            mosi = 0;
            #(SCLK_PERIOD);
        end
    endtask

    // Main Test Sequence
    initial begin
        logic [DATA_WIDTH-1:0] master_tx_data;
        logic [DATA_WIDTH-1:0] slave_tx_data;
        logic [DATA_WIDTH-1:0] master_rx_data;
        
        // Setup
        $dumpfile("spi_slave_tb.vcd");
        $dumpvars(0, spi_slave_tb);
        
        $display("---------------------------------------");
        $display("   Starting SPI Slave Self-Checking TB ");
        $display("---------------------------------------");
        
        // Reset
        rst = 1;
        #50 rst = 0;
        #100;
        
        // --- Test 1: Single Byte Exchange ---
        master_tx_data = 8'hA5;
        slave_tx_data  = 8'h55;
        
        $display("[Test 1] Loading Slave with 0x%h...", slave_tx_data);
        
        // Load Slave
        wait(tx_ready);
        @(posedge clk);
        tx_data_in = slave_tx_data;
        tx_valid = 1;
        @(posedge clk);
        tx_valid = 0;
        
        // Run SPI transaction
        spi_transfer(master_tx_data, master_rx_data);
        
        // Check Master received correct data from Slave
        if (master_rx_data !== slave_tx_data) begin
            $display("ERROR: Master Received 0x%h, Expected 0x%h", master_rx_data, slave_tx_data);
            error_count++;
        end else begin
            $display("SUCCESS: Master Received 0x%h", master_rx_data);
        end

        // Check Slave received correct data from Master
        // We need to wait for rx_valid pulse or check it was set
        @(posedge clk);
        if (rx_data !== master_tx_data) begin
            $display("ERROR: Slave Received 0x%h, Expected 0x%h", rx_data, master_tx_data);
            error_count++;
        end else begin
             $display("SUCCESS: Slave Received 0x%h", rx_data);
        end

        // --- Test 2: Randomized Streaming ---
        $display("\n[Test 2] Randomized Streaming Test (10 Iterations)");
        
        for (int k = 0; k < 10; k++) begin
            master_tx_data = $random;
            slave_tx_data  = $random;
            
            // 1. Load Slave with data for this turn
            wait(tx_ready);
            @(posedge clk);
            tx_data_in = slave_tx_data;
            tx_valid = 1;
            @(posedge clk);
            tx_valid = 0;
            
            // 2. Perform Transaction
            spi_transfer(master_tx_data, master_rx_data);
            
            // 3. Verify Master RX (MISO)
            if (master_rx_data !== slave_tx_data) begin
                $display("ITER %0d FAIL: Master RX=0x%h Exp=0x%h", k, master_rx_data, slave_tx_data);
                error_count++;
            end
            
            // 4. Verify Slave RX (MOSI)
            // Wait for data valid if needed, but the task waits long enough for the slave to latch
            if (rx_data !== master_tx_data) begin
                 $display("ITER %0d FAIL: Slave RX=0x%h Exp=0x%h", k, rx_data, master_tx_data);
                 error_count++;
            end
            
            // Short random delay between transactions
            repeat($urandom_range(5, 20)) @(posedge clk);
        end
        
        // Summary
        $display("---------------------------------------");
        if (error_count == 0) begin
             $display("TEST PASSED: All checks successful.");
        end else begin
             $display("TEST FAILED: %0d errors found.", error_count);
        end
        $display("---------------------------------------");
        
        $finish;
    end

endmodule

SPIQuadCopter/spiSlave/spi_slave_tb.vcd
$date
	Sat Jan 17 11:08:36 2026
$end
$version
	Icarus Verilog
$end
$timescale
	1ps
$end
$scope module spi_slave_tb $end
$var wire 1 ! tx_ready $end
$var wire 1 " rx_valid $end
$var wire 8 # rx_data [7:0] $end
$var wire 1 $ miso $end
$var wire 1 % busy $end
$var parameter 32 & CLK_PERIOD $end
$var parameter 32 ' DATA_WIDTH $end
$var parameter 32 ( SCLK_PERIOD $end
$var reg 1 ) clk $end
$var reg 1 * cs_n $end
$var reg 1 + mosi $end
$var reg 1 , rst $end
$var reg 1 - sclk $end
$var reg 8 . tx_data_in [7:0] $end
$var reg 1 / tx_valid $end
$var integer 32 0 error_count [31:0] $end
$scope module dut $end
$var wire 1 1 cs_active $end
$var wire 1 ) i_clk $end
$var wire 1 * i_cs_n $end
$var wire 1 + i_mosi $end
$var wire 1 , i_rst $end
$var wire 1 - i_sclk $end
$var wire 8 2 i_tx_data [7:0] $end
$var wire 1 / i_tx_valid $end
$var wire 1 % o_busy $end
$var wire 1 3 sclk_rising $end
$var wire 1 4 sclk_falling $end
$var wire 1 $ o_miso $end
$var wire 1 5 o_cs_n_sync $end
$var parameter 32 6 DATA_WIDTH $end
$var reg 3 7 bit_cnt [2:0] $end
$var reg 3 8 cs_n_sync [2:0] $end
$var reg 2 9 mosi_sync [1:0] $end
$var reg 1 " o_data_valid $end
$var reg 8 : o_rx_data [7:0] $end
$var reg 1 ! o_tx_ready $end
$var reg 8 ; rx_shift_reg [7:0] $end
$var reg 3 < sclk_sync [2:0] $end
$var reg 8 = tx_holding_reg [7:0] $end
$var reg 8 > tx_shift_reg [7:0] $end
$upscope $end
$scope begin $unm_blk_20 $end
$var reg 8 ? master_rx_data [7:0] $end
$var reg 8 @ master_tx_data [7:0] $end
$var reg 8 A slave_tx_data [7:0] $end
$scope begin $ivl_for_loop0 $end
$var integer 32 B k [31:0] $end
$upscope $end
$upscope $end
$scope task spi_transfer $end
$upscope $end
$upscope $end
$enddefinitions $end
$comment Show the parameter values. $end
$dumpall
b1000 6
b110010 (
b1000 '
b1010 &
$end
#0
$dumpvars
b0 B
bx A
bx @
bx ?
bx >
bx =
bx <
bx ;
bx :
bx 9
bx 8
bx 7
x5
x4
x3
bx 2
x1
b0 0
0/
bx .
0-
1,
0+
1*
0)
x%
x$
bx #
x"
x!
$end
#5000
z$
0%
01
15
03
04
b0 9
b111 8
b0 <
1!
b0 =
b0 >
b0 ;
0"
b0 #
b0 :
b111 7
1)
#10000
0)
#15000
1)
#20000
0)
#25000
1)
#30000
0)
#35000
1)
#40000
0)
#45000
1)
#50000
0)
0,
#55000
1)
#60000
0)
#65000
1)
#70000
0)
#75000
1)
#80000
0)
#85000
1)
#90000
0)
#95000
1)
#100000
0)
#105000
1)
#110000
0)
#115000
1)
#120000
0)
#125000
1)
#130000
0)
#135000
1)
#140000
0)
#145000
1)
#150000
0)
b1010101 A
b10100101 @
#155000
0!
b1010101 =
1/
b1010101 .
b1010101 2
1)
#160000
0)
#165000
b110 8
1!
b1010101 >
0*
0/
1)
#170000
0)
#175000
0$
1%
11
05
b100 8
1)
#180000
0)
#185000
b0 8
1)
#190000
0)
#195000
1)
#200000
0)
#205000
1)
#210000
0)
#215000
b1 9
1)
1+
#220000
0)
#225000
b11 9
1)
#230000
0)
#235000
1)
#240000
0)
1-
#245000
b1 <
1)
#250000
0)
#255000
13
b11 <
1)
#260000
0)
#265000
03
b10 9
b110 <
b1 ;
1)
0+
0-
#270000
0)
#275000
14
b0 9
b100 <
1)
#280000
0)
#285000
1$
04
b0 <
b10101010 >
b110 7
1)
#290000
0)
1-
#295000
b1 <
1)
#300000
0)
#305000
13
b11 <
1)
#310000
0)
#315000
03
b10 ;
b1 9
b110 <
1)
1+
0-
#320000
0)
#325000
14
b11 9
b100 <
1)
#330000
0)
#335000
0$
04
b1010100 >
b101 7
b0 <
1)
#340000
0)
1-
#345000
b1 <
1)
#350000
0)
#355000
13
b11 <
1)
#360000
0)
#365000
03
b10 9
b110 <
b101 ;
1)
0+
0-
#370000
0)
#375000
14
b0 9
b100 <
1)
#380000
0)
#385000
1$
04
b0 <
b10101000 >
b100 7
1)
#390000
0)
1-
#395000
b1 <
1)
#400000
0)
#405000
13
b11 <
1)
#410000
0)
#415000
03
b1010 ;
b110 <
1)
0-
#420000
0)
#425000
14
b100 <
1)
#430000
0)
#435000
0$
04
b1010000 >
b11 7
b0 <
1)
#440000
0)
1-
#445000
b1 <
1)
#450000
0)
#455000
13
b11 <
1)
#460000
0)
#465000
03
b1 9
b110 <
b10100 ;
1)
1+
0-
#470000
0)
#475000
14
b11 9
b100 <
1)
#480000
0)
#485000
1$
04
b0 <
b10100000 >
b10 7
1)
#490000
0)
1-
#495000
b1 <
1)
#500000
0)
#505000
13
b11 <
1)
#510000
0)
#515000
03
b101001 ;
b10 9
b110 <
1)
0+
0-
#520000
0)
#525000
14
b0 9
b100 <
1)
#530000
0)
#535000
0$
04
b1000000 >
b1 7
b0 <
1)
#540000
0)
1-
#545000
b1 <
1)
#550000
0)
#555000
13
b11 <
1)
#560000
0)
#565000
03
b1 9
b110 <
b1010010 ;
1)
1+
0-
#570000
0)
#575000
14
b11 9
b100 <
1)
#580000
0)
#585000
1$
04
b0 <
b10000000 >
b0 7
1)
#590000
0)
1-
#595000
b1 <
1)
#600000
0)
#605000
13
b11 <
1)
#610000
0)
#615000
03
1"
b10100101 #
b10100101 :
b10100101 ;
b110 <
1)
0-
#620000
0)
#625000
14
b100 <
0"
1)
#630000
0)
#635000
0$
04
b0 >
b111 7
b0 <
1)
#640000
0)
0+
1*
#645000
b10 9
b1 8
1)
#650000
0)
#655000
z$
0%
01
15
b0 9
b11 8
1)
#660000
0)
#665000
b111 8
1)
#670000
0)
#675000
1)
#680000
0)
#685000
1)
#690000
0)
b1010101 ?
#695000
b10000001 A
b100100 @
1)
#700000
0)
#705000
0!
b10000001 =
1/
b10000001 .
b10000001 2
1)
#710000
0)
#715000
1!
b10000001 >
b110 8
0*
0/
1)
#720000
0)
#725000
1$
1%
11
05
b100 8
1)
#730000
0)
#735000
b0 8
1)
#740000
0)
#745000
1)
#750000
0)
#755000
1)
#760000
0)
#765000
1)
#770000
0)
#775000
1)
#780000
0)
#785000
1)
#790000
0)
1-
#795000
b1 <
1)
#800000
0)
#805000
13
b11 <
1)
#810000
0)
#815000
03
b1001010 ;
b110 <
1)
0-
#820000
0)
#825000
14
b100 <
1)
#830000
0)
#835000
0$
04
b10 >
b110 7
b0 <
1)
#840000
0)
1-
#845000
b1 <
1)
#850000
0)
#855000
13
b11 <
1)
#860000
0)
#865000
03
b1 9
b110 <
b10010100 ;
1)
1+
0-
#870000
0)
#875000
14
b11 9
b100 <
1)
#880000
0)
#885000
04
b0 <
b100 >
b101 7
1)
#890000
0)
1-
#895000
b1 <
1)
#900000
0)
#905000
13
b11 <
1)
#910000
0)
#915000
03
b101001 ;
b10 9
b110 <
1)
0+
0-
#920000
0)
#925000
14
b0 9
b100 <
1)
#930000
0)
#935000
04
b1000 >
b100 7
b0 <
1)
#940000
0)
1-
#945000
b1 <
1)
#950000
0)
#955000
13
b11 <
1)
#960000
0)
#965000
03
b110 <
b1010010 ;
1)
0-
#970000
0)
#975000
14
b100 <
1)
#980000
0)
#985000
04
b0 <
b10000 >
b11 7
1)
#990000
0)
1-
#995000
b1 <
1)
#1000000
0)
#1005000
13
b11 <
1)
#1010000
0)
#1015000
03
b10100100 ;
b1 9
b110 <
1)
1+
0-
#1020000
0)
#1025000
14
b11 9
b100 <
1)
#1030000
0)
#1035000
04
b100000 >
b10 7
b0 <
1)
#1040000
0)
1-
#1045000
b1 <
1)
#1050000
0)
#1055000
13
b11 <
1)
#1060000
0)
#1065000
03
b10 9
b110 <
b1001001 ;
1)
0+
0-
#1070000
0)
#1075000
14
b0 9
b100 <
1)
#1080000
0)
#1085000
04
b0 <
b1000000 >
b1 7
1)
#1090000
0)
1-
#1095000
b1 <
1)
#1100000
0)
#1105000
13
b11 <
1)
#1110000
0)
#1115000
03
b10010010 ;
b110 <
1)
0-
#1120000
0)
#1125000
14
b100 <
1)
#1130000
0)
#1135000
1$
04
b10000000 >
b0 7
b0 <
1)
#1140000
0)
1-
#1145000
b1 <
1)
#1150000
0)
#1155000
13
b11 <
1)
#1160000
0)
#1165000
03
b110 <
1"
b100100 #
b100100 :
b100100 ;
1)
0-
#1170000
0)
#1175000
14
0"
b100 <
1)
#1180000
0)
#1185000
0$
04
b0 <
b0 >
b111 7
1)
#1190000
0)
1*
#1195000
b1 8
1)
#1200000
0)
#1205000
z$
0%
01
15
b11 8
1)
#1210000
0)
#1215000
b111 8
1)
#1220000
0)
#1225000
1)
#1230000
0)
#1235000
1)
#1240000
0)
b10000001 ?
#1245000
1)
#1250000
0)
#1255000
1)
#1260000
0)
#1265000
1)
#1270000
0)
#1275000
1)
#1280000
0)
#1285000
1)
#1290000
0)
#1295000
1)
#1300000
0)
#1305000
1)
#1310000
0)
#1315000
1)
#1320000
0)
#1325000
1)
#1330000
0)
#1335000
1)
#1340000
0)
#1345000
1)
#1350000
0)
#1355000
1)
#1360000
0)
#1365000
1)
#1370000
0)
#1375000
b1100011 A
b1001 @
b1 B
1)
#1380000
0)
#1385000
0!
b1100011 =
1/
b1100011 .
b1100011 2
1)
#1390000
0)
#1395000
1!
b1100011 >
b110 8
0*
0/
1)
#1400000
0)
#1405000
0$
1%
11
05
b100 8
1)
#1410000
0)
#1415000
b0 8
1)
#1420000
0)
#1425000
1)
#1430000
0)
#1435000
1)
#1440000
0)
#1445000
1)
#1450000
0)
#1455000
1)
#1460000
0)
#1465000
1)
#1470000
0)
1-
#1475000
b1 <
1)
#1480000
0)
#1485000
13
b11 <
1)
#1490000
0)
#1495000
03
b1001000 ;
b110 <
1)
0-
#1500000
0)
#1505000
14
b100 <
1)
#1510000
0)
#1515000
1$
04
b11000110 >
b110 7
b0 <
1)
#1520000
0)
1-
#1525000
b1 <
1)
#1530000
0)
#1535000
13
b11 <
1)
#1540000
0)
#1545000
03
b110 <
b10010000 ;
1)
0-
#1550000
0)
#1555000
14
b100 <
1)
#1560000
0)
#1565000
04
b0 <
b10001100 >
b101 7
1)
#1570000
0)
1-
#1575000
b1 <
1)
#1580000
0)
#1585000
13
b11 <
1)
#1590000
0)
#1595000
03
b100000 ;
b110 <
1)
0-
#1600000
0)
#1605000
14
b100 <
1)
#1610000
0)
#1615000
0$
04
b11000 >
b100 7
b0 <
1)
#1620000
0)
1-
#1625000
b1 <
1)
#1630000
0)
#1635000
13
b11 <
1)
#1640000
0)
#1645000
03
b1 9
b110 <
b1000000 ;
1)
1+
0-
#1650000
0)
#1655000
14
b11 9
b100 <
1)
#1660000
0)
#1665000
04
b0 <
b110000 >
b11 7
1)
#1670000
0)
1-
#1675000
b1 <
1)
#1680000
0)
#1685000
13
b11 <
1)
#1690000
0)
#1695000
03
b10000001 ;
b10 9
b110 <
1)
0+
0-
#1700000
0)
#1705000
14
b0 9
b100 <
1)
#1710000
0)
#1715000
04
b1100000 >
b10 7
b0 <
1)
#1720000
0)
1-
#1725000
b1 <
1)
#1730000
0)
#1735000
13
b11 <
1)
#1740000
0)
#1745000
03
b110 <
b10 ;
1)
0-
#1750000
0)
#1755000
14
b100 <
1)
#1760000
0)
#1765000
1$
04
b0 <
b11000000 >
b1 7
1)
#1770000
0)
1-
#1775000
b1 <
1)
#1780000
0)
#1785000
13
b11 <
1)
#1790000
0)
#1795000
03
b100 ;
b1 9
b110 <
1)
1+
0-
#1800000
0)
#1805000
14
b11 9
b100 <
1)
#1810000
0)
#1815000
04
b10000000 >
b0 7
b0 <
1)
#1820000
0)
1-
#1825000
b1 <
1)
#1830000
0)
#1835000
13
b11 <
1)
#1840000
0)
#1845000
03
b110 <
1"
b1001 #
b1001 :
b1001 ;
1)
0-
#1850000
0)
#1855000
14
0"
b100 <
1)
#1860000
0)
#1865000
0$
04
b0 <
b0 >
b111 7
1)
#1870000
0)
0+
1*
#1875000
b10 9
b1 8
1)
#1880000
0)
#1885000
z$
0%
01
15
b0 9
b11 8
1)
#1890000
0)
#1895000
b111 8
1)
#1900000
0)
#1905000
1)
#1910000
0)
#1915000
1)
#1920000
0)
b1100011 ?
#1925000
1)
#1930000
0)
#1935000
1)
#1940000
0)
#1945000
1)
#1950000
0)
#1955000
1)
#1960000
0)
#1965000
1)
#1970000
0)
#1975000
1)
#1980000
0)
#1985000
1)
#1990000
0)
#1995000
1)
#2000000
0)
#2005000
b10001101 A
b1101 @
b10 B
1)
#2010000
0)
#2015000
0!
b10001101 =
1/
b10001101 .
b10001101 2
1)
#2020000
0)
#2025000
b110 8
1!
b10001101 >
0*
0/
1)
#2030000
0)
#2035000
1$
1%
11
05
b100 8
1)
#2040000
0)
#2045000
b0 8
1)
#2050000
0)
#2055000
1)
#2060000
0)
#2065000
1)
#2070000
0)
#2075000
1)
#2080000
0)
#2085000
1)
#2090000
0)
#2095000
1)
#2100000
0)
1-
#2105000
b1 <
1)
#2110000
0)
#2115000
13
b11 <
1)
#2120000
0)
#2125000
03
b110 <
b10010 ;
1)
0-
#2130000
0)
#2135000
14
b100 <
1)
#2140000
0)
#2145000
0$
04
b0 <
b11010 >
b110 7
1)
#2150000
0)
1-
#2155000
b1 <
1)
#2160000
0)
#2165000
13
b11 <
1)
#2170000
0)
#2175000
03
b100100 ;
b110 <
1)
0-
#2180000
0)
#2185000
14
b100 <
1)
#2190000
0)
#2195000
04
b110100 >
b101 7
b0 <
1)
#2200000
0)
1-
#2205000
b1 <
1)
#2210000
0)
#2215000
13
b11 <
1)
#2220000
0)
#2225000
03
b110 <
b1001000 ;
1)
0-
#2230000
0)
#2235000
14
b100 <
1)
#2240000
0)
#2245000
04
b0 <
b1101000 >
b100 7
1)
#2250000
0)
1-
#2255000
b1 <
1)
#2260000
0)
#2265000
13
b11 <
1)
#2270000
0)
#2275000
03
b10010000 ;
b1 9
b110 <
1)
1+
0-
#2280000
0)
#2285000
14
b11 9
b100 <
1)
#2290000
0)
#2295000
1$
04
b11010000 >
b11 7
b0 <
1)
#2300000
0)
1-
#2305000
b1 <
1)
#2310000
0)
#2315000
13
b11 <
1)
#2320000
0)
#2325000
03
b110 <
b100001 ;
1)
0-
#2330000
0)
#2335000
14
b100 <
1)
#2340000
0)
#2345000
04
b0 <
b10100000 >
b10 7
1)
#2350000
0)
1-
#2355000
b1 <
1)
#2360000
0)
#2365000
13
b11 <
1)
#2370000
0)
#2375000
03
b1000011 ;
b10 9
b110 <
1)
0+
0-
#2380000
0)
#2385000
14
b0 9
b100 <
1)
#2390000
0)
#2395000
0$
04
b1000000 >
b1 7
b0 <
1)
#2400000
0)
1-
#2405000
b1 <
1)
#2410000
0)
#2415000
13
b11 <
1)
#2420000
0)
#2425000
03
b1 9
b110 <
b10000110 ;
1)
1+
0-
#2430000
0)
#2435000
14
b11 9
b100 <
1)
#2440000
0)
#2445000
1$
04
b0 <
b10000000 >
b0 7
1)
#2450000
0)
1-
#2455000
b1 <
1)
#2460000
0)
#2465000
13
b11 <
1)
#2470000
0)
#2475000
03
1"
b1101 #
b1101 :
b1101 ;
b110 <
1)
0-
#2480000
0)
#2485000
14
b100 <
0"
1)
#2490000
0)
#2495000
0$
04
b0 >
b111 7
b0 <
1)
#2500000
0)
0+
1*
#2505000
b10 9
b1 8
1)
#2510000
0)
#2515000
z$
0%
01
15
b0 9
b11 8
1)
#2520000
0)
#2525000
b111 8
1)
#2530000
0)
#2535000
1)
#2540000
0)
#2545000
1)
#2550000
0)
b10001101 ?
#2555000
1)
#2560000
0)
#2565000
1)
#2570000
0)
#2575000
1)
#2580000
0)
#2585000
1)
#2590000
0)
#2595000
b10010 A
b1100101 @
b11 B
1)
#2600000
0)
#2605000
0!
b10010 =
1/
b10010 .
b10010 2
1)
#2610000
0)
#2615000
1!
b10010 >
b110 8
0*
0/
1)
#2620000
0)
#2625000
0$
1%
11
05
b100 8
1)
#2630000
0)
#2635000
b0 8
1)
#2640000
0)
#2645000
1)
#2650000
0)
#2655000
1)
#2660000
0)
#2665000
1)
#2670000
0)
#2675000
1)
#2680000
0)
#2685000
1)
#2690000
0)
1-
#2695000
b1 <
1)
#2700000
0)
#2705000
13
b11 <
1)
#2710000
0)
#2715000
03
b11010 ;
b1 9
b110 <
1)
1+
0-
#2720000
0)
#2725000
14
b11 9
b100 <
1)
#2730000
0)
#2735000
04
b100100 >
b110 7
b0 <
1)
#2740000
0)
1-
#2745000
b1 <
1)
#2750000
0)
#2755000
13
b11 <
1)
#2760000
0)
#2765000
03
b110 <
b110101 ;
1)
0-
#2770000
0)
#2775000
14
b100 <
1)
#2780000
0)
#2785000
04
b0 <
b1001000 >
b101 7
1)
#2790000
0)
1-
#2795000
b1 <
1)
#2800000
0)
#2805000
13
b11 <
1)
#2810000
0)
#2815000
03
b1101011 ;
b10 9
b110 <
1)
0+
0-
#2820000
0)
#2825000
14
b0 9
b100 <
1)
#2830000
0)
#2835000
1$
04
b10010000 >
b100 7
b0 <
1)
#2840000
0)
1-
#2845000
b1 <
1)
#2850000
0)
#2855000
13
b11 <
1)
#2860000
0)
#2865000
03
b110 <
b11010110 ;
1)
0-
#2870000
0)
#2875000
14
b100 <
1)
#2880000
0)
#2885000
0$
04
b0 <
b100000 >
b11 7
1)
#2890000
0)
1-
#2895000
b1 <
1)
#2900000
0)
#2905000
13
b11 <
1)
#2910000
0)
#2915000
03
b10101100 ;
b1 9
b110 <
1)
1+
0-
#2920000
0)
#2925000
14
b11 9
b100 <
1)
#2930000
0)
#2935000
04
b1000000 >
b10 7
b0 <
1)
#2940000
0)
1-
#2945000
b1 <
1)
#2950000
0)
#2955000
13
b11 <
1)
#2960000
0)
#2965000
03
b10 9
b110 <
b1011001 ;
1)
0+
0-
#2970000
0)
#2975000
14
b0 9
b100 <
1)
#2980000
0)
#2985000
1$
04
b0 <
b10000000 >
b1 7
1)
#2990000
0)
1-
#2995000
b1 <
1)
#3000000
0)
#3005000
13
b11 <
1)
#3010000
0)
#3015000
03
b10110010 ;
b1 9
b110 <
1)
1+
0-
#3020000
0)
#3025000
14
b11 9
b100 <
1)
#3030000
0)
#3035000
0$
04
b0 >
b0 7
b0 <
1)
#3040000
0)
1-
#3045000
b1 <
1)
#3050000
0)
#3055000
13
b11 <
1)
#3060000
0)
#3065000
03
b110 <
1"
b1100101 #
b1100101 :
b1100101 ;
1)
0-
#3070000
0)
#3075000
14
0"
b100 <
1)
#3080000
0)
#3085000
04
b0 <
b111 7
1)
#3090000
0)
0+
1*
#3095000
b10 9
b1 8
1)
#3100000
0)
#3105000
z$
0%
01
15
b0 9
b11 8
1)
#3110000
0)
#3115000
b111 8
1)
#3120000
0)
#3125000
1)
#3130000
0)
#3135000
1)
#3140000
0)
b10010 ?
#3145000
1)
#3150000
0)
#3155000
1)
#3160000
0)
#3165000
1)
#3170000
0)
#3175000
1)
#3180000
0)
#3185000
1)
#3190000
0)
#3195000
1)
#3200000
0)
#3205000
1)
#3210000
0)
#3215000
b1101 A
b1 @
b100 B
1)
#3220000
0)
#3225000
0!
b1101 =
1/
b1101 .
b1101 2
1)
#3230000
0)
#3235000
1!
b1101 >
b110 8
0*
0/
1)
#3240000
0)
#3245000
0$
1%
11
05
b100 8
1)
#3250000
0)
#3255000
b0 8
1)
#3260000
0)
#3265000
1)
#3270000
0)
#3275000
1)
#3280000
0)
#3285000
1)
#3290000
0)
#3295000
1)
#3300000
0)
#3305000
1)
#3310000
0)
1-
#3315000
b1 <
1)
#3320000
0)
#3325000
13
b11 <
1)
#3330000
0)
#3335000
03
b11001010 ;
b110 <
1)
0-
#3340000
0)
#3345000
14
b100 <
1)
#3350000
0)
#3355000
04
b11010 >
b110 7
b0 <
1)
#3360000
0)
1-
#3365000
b1 <
1)
#3370000
0)
#3375000
13
b11 <
1)
#3380000
0)
#3385000
03
b110 <
b10010100 ;
1)
0-
#3390000
0)
#3395000
14
b100 <
1)
#3400000
0)
#3405000
04
b0 <
b110100 >
b101 7
1)
#3410000
0)
1-
#3415000
b1 <
1)
#3420000
0)
#3425000
13
b11 <
1)
#3430000
0)
#3435000
03
b101000 ;
b110 <
1)
0-
#3440000
0)
#3445000
14
b100 <
1)
#3450000
0)
#3455000
04
b1101000 >
b100 7
b0 <
1)
#3460000
0)
1-
#3465000
b1 <
1)
#3470000
0)
#3475000
13
b11 <
1)
#3480000
0)
#3485000
03
b110 <
b1010000 ;
1)
0-
#3490000
0)
#3495000
14
b100 <
1)
#3500000
0)
#3505000
1$
04
b0 <
b11010000 >
b11 7
1)
#3510000
0)
1-
#3515000
b1 <
1)
#3520000
0)
#3525000
13
b11 <
1)
#3530000
0)
#3535000
03
b10100000 ;
b110 <
1)
0-
#3540000
0)
#3545000
14
b100 <
1)
#3550000
0)
#3555000
04
b10100000 >
b10 7
b0 <
1)
#3560000
0)
1-
#3565000
b1 <
1)
