SPIQuadCopter/spiSlave/spi_slave.sv
/**
 * SPI Slave Module (Mode 0)
 * 
 * Mode 0: CPOL=0, CPHA=0
 * - Clock idle state: LOW
 * - Data sampled on leading (rising) edge
 * - Data changed on trailing (falling) edge
 * 
 * Features:
 * - 8-bit data width
 * - 2-FF synchronizer for clock domain crossing
 * - Configurable clock polarity and phase (currently hardcoded to Mode 0)
 */

module spi_slave #(
    parameter DATA_WIDTH = 8
) (
    // Clock and Reset
    input  logic                    i_clk,
    input  logic                    i_rst_n,
    
    // SPI Interface
    input  logic                    i_sclk,       // SPI Clock
    input  logic                    i_cs_n,       // Chip Select (active low)
    input  logic                    i_mosi,       // Master Out Slave In
    output logic                    o_miso,       // Master In Slave Out
    
    // Slave Interface (to internal module)
    output logic [DATA_WIDTH-1:0]   o_rx_data,    // Received data
    output logic                    o_rx_valid,   // Received data valid pulse
    input  logic [DATA_WIDTH-1:0]   i_tx_data,    // Data to transmit
    input  logic                    i_tx_valid,   // Load new transmit data
    output logic                    o_busy        // SPI transaction in progress
);

    // =============================
    // 2-FF Synchronizer for SCLK
    // =============================
    logic sclk_sync1, sclk_sync2;
    logic sclk_r1, sclk_r2;
    
    always_ff @(posedge i_clk or negedge i_rst_n) begin
        if (!i_rst_n) begin
            sclk_sync1 <= 1'b0;
            sclk_sync2 <= 1'b0;
        end else begin
            sclk_sync1 <= i_sclk;
            sclk_sync2 <= sclk_sync1;
        end
    end
    
    // =============================
    // 2-FF Synchronizer for CS_N
    // =============================
    logic cs_n_sync1, cs_n_sync2;
    
    always_ff @(posedge i_clk or negedge i_rst_n) begin
        if (!i_rst_n) begin
            cs_n_sync1 <= 1'b1;
            cs_n_sync2 <= 1'b1;
        end else begin
            cs_n_sync1 <= i_cs_n;
            cs_n_sync2 <= cs_n_sync1;
        end
    end
    
    // =============================
    // 2-FF Synchronizer for MOSI
    // =============================
    logic mosi_sync1, mosi_sync2;
    
    always_ff @(posedge i_clk or negedge i_rst_n) begin
        if (!i_rst_n) begin
            mosi_sync1 <= 1'b0;
            mosi_sync2 <= 1'b0;
        end else begin
            mosi_sync1 <= i_mosi;
            mosi_sync2 <= mosi_sync1;
        end
    end
    
    // Edge Detection for SCLK (detect rising edge for Mode 0)
    always_ff @(posedge i_clk or negedge i_rst_n) begin
        if (!i_rst_n) begin
            sclk_r1 <= 1'b0;
            sclk_r2 <= 1'b0;
        end else begin
            sclk_r1 <= sclk_sync2;
            sclk_r2 <= sclk_r1;
        end
    end
    
    logic sclk_rising_edge;
    assign sclk_rising_edge = sclk_r1 && !sclk_r2;
    
    logic sclk_falling_edge;
    assign sclk_falling_edge = !sclk_r1 && sclk_r2;
    
    // =============================
    // Shift Register and Control Logic
    // =============================
    logic [DATA_WIDTH-1:0] shift_reg;
    logic [2:0]            bit_count;
    logic [DATA_WIDTH-1:0] tx_shift_reg;
    
    // Track previous CS state
    logic cs_n_r;
    always_ff @(posedge i_clk or negedge i_rst_n) begin
        if (!i_rst_n)
            cs_n_r <= 1'b1;
        else
            cs_n_r <= cs_n_sync2;
    end
    
    logic cs_falling_edge;
    assign cs_falling_edge = cs_n_r && !cs_n_sync2;
    
    // Main SPI Slave Logic
    always_ff @(posedge i_clk or negedge i_rst_n) begin
        if (!i_rst_n) begin
            shift_reg     <= '0;
            bit_count     <= '0;
            o_rx_valid    <= 1'b0;
            tx_shift_reg  <= '0;
            o_miso        <= 1'b0;
            o_busy        <= 1'b0;
        end else begin
            o_rx_valid <= 1'b0;  // Default: pulse valid for one clock
            
            // CS goes low - start transaction
            if (cs_falling_edge) begin
                bit_count <= '0;
                o_busy    <= 1'b1;
                // Load transmit data if available
                if (i_tx_valid)
                    tx_shift_reg <= i_tx_data;
                else
                    tx_shift_reg <= '0;
                // Set MISO to MSB of tx data
                o_miso <= i_tx_valid ? i_tx_data[DATA_WIDTH-1] : 1'b0;
            end
            // CS is high - transaction ended
            else if (cs_n_sync2) begin
                o_busy <= 1'b0;
                o_miso <= 1'b0;
            end
            // CS is low and we see SCLK rising edge - sample MOSI
            else if (sclk_rising_edge && !cs_n_sync2) begin
                shift_reg <= {shift_reg[DATA_WIDTH-2:0], mosi_sync2};
                bit_count <= bit_count + 1'b1;
                
                // After 8 bits received
                if (bit_count == (DATA_WIDTH - 1)) begin
                    o_rx_data <= {shift_reg[DATA_WIDTH-2:0], mosi_sync2};
                    o_rx_valid <= 1'b1;
                    bit_count <= '0;
                end
            end
            // SCLK falling edge - shift out next MISO bit
            else if (sclk_falling_edge && !cs_n_sync2) begin
                if (bit_count < DATA_WIDTH) begin
                    tx_shift_reg <= {tx_shift_reg[DATA_WIDTH-2:0], 1'b0};
                    o_miso <= tx_shift_reg[DATA_WIDTH-1];
                end
            end
            
            // Load new transmit data when requested
            if (i_tx_valid) begin
                tx_shift_reg <= i_tx_data;
            end
        end
    end

endmodule

SPIQuadCopter/spiSlave/spi_slave_tb.sv
/**
 * SPI Slave Testbench
 * 
 * Tests the SPI Slave module in Mode 0 operation
 */

`timescale 1ns/1ps

module spi_slave_tb;

    // =============================
    // Parameters and Signals
    // =============================
    parameter DATA_WIDTH = 8;
    parameter SYS_CLK_PERIOD = 10;  // 100 MHz system clock
    parameter SPI_CLK_PERIOD = 40;  // 25 MHz SPI clock
    
    logic                    sys_clk;
    logic                    rst_n;
    logic                    i_sclk;
    logic                    i_cs_n;
    logic                    i_mosi;
    logic                    o_miso;
    logic [DATA_WIDTH-1:0]   o_rx_data;
    logic                    o_rx_valid;
    logic [DATA_WIDTH-1:0]   i_tx_data;
    logic                    i_tx_valid;
    logic                    o_busy;
    
    // =============================
    // DUT Instantiation
    // =============================
    spi_slave dut (
        .i_clk       (sys_clk),
        .i_rst_n     (rst_n),
        .i_sclk      (i_sclk),
        .i_cs_n      (i_cs_n),
        .i_mosi      (i_mosi),
        .o_miso      (o_miso),
        .o_rx_data   (o_rx_data),
        .o_rx_valid  (o_rx_valid),
        .i_tx_data   (i_tx_data),
        .i_tx_valid  (i_tx_valid),
        .o_busy      (o_busy)
    );
    
    // =============================
    // Clock Generation
    // =============================
    initial begin
        sys_clk = 1'b0;
        forever #(SYS_CLK_PERIOD/2) sys_clk = ~sys_clk;
    end
    
    initial begin
        i_sclk = 1'b0;
        forever #(SPI_CLK_PERIOD/2) i_sclk = ~i_sclk;
    end
    
    // =============================
    // Testbench Stimulus
    // =============================
    initial begin
        // File for waveform dump
        $dumpfile("spi_slave_tb.vcd");
        $dumpvars(0, spi_slave_tb);
        
        // Initialize
        rst_n = 1'b0;
        i_cs_n = 1'b1;
        i_mosi = 1'b0;
        i_tx_data = 8'h00;
        i_tx_valid = 1'b0;
        
        // Wait for reset
        repeat(10) @(posedge sys_clk);
        rst_n = 1'b1;
        
        repeat(10) @(posedge sys_clk);
        
        // ===========================
        // Test 1: Simple SPI Transfer
        // ===========================
        $display("Test 1: Simple SPI Transfer");
        $display("Master sends: 0xA5 (10100101)");
        $display("Slave sends: 0x5A (01011010)");
        
        // Load slave transmit data
        @(posedge sys_clk) i_tx_data = 8'h5A;
        @(posedge sys_clk) i_tx_valid = 1'b1;
        @(posedge sys_clk) i_tx_valid = 1'b0;
        
        // Start SPI transaction
        repeat(5) @(posedge sys_clk);
        @(posedge sys_clk) i_cs_n = 1'b0;
        
        // Wait for synchronization
        repeat(10) @(posedge sys_clk);
        
        // Send byte: 0xA5
        send_spi_byte(8'hA5);
        
        // Wait for synchronization
        repeat(10) @(posedge sys_clk);
        
        // End transaction
        @(posedge sys_clk) i_cs_n = 1'b1;
        
        repeat(20) @(posedge sys_clk);
        
        // ===========================
        // Test 2: Multiple Transfers
        // ===========================
        $display("\nTest 2: Multiple Transfers");
        
        repeat(5) @(posedge sys_clk);
        
        // Transfer 1
        $display("Transfer 1: Master sends 0x12, Slave sends 0x34");
        @(posedge sys_clk) i_tx_data = 8'h34;
        @(posedge sys_clk) i_tx_valid = 1'b1;
        @(posedge sys_clk) i_tx_valid = 1'b0;
        
        repeat(5) @(posedge sys_clk);
        @(posedge sys_clk) i_cs_n = 1'b0;
        repeat(10) @(posedge sys_clk);
        
        send_spi_byte(8'h12);
        
        repeat(10) @(posedge sys_clk);
        @(posedge sys_clk) i_cs_n = 1'b1;
        
        repeat(10) @(posedge sys_clk);
        
        // Transfer 2
        $display("Transfer 2: Master sends 0xAB, Slave sends 0xCD");
        @(posedge sys_clk) i_tx_data = 8'hCD;
        @(posedge sys_clk) i_tx_valid = 1'b1;
        @(posedge sys_clk) i_tx_valid = 1'b0;
        
        repeat(5) @(posedge sys_clk);
        @(posedge sys_clk) i_cs_n = 1'b0;
        repeat(10) @(posedge sys_clk);
        
        send_spi_byte(8'hAB);
        
        repeat(10) @(posedge sys_clk);
        @(posedge sys_clk) i_cs_n = 1'b1;
        
        repeat(20) @(posedge sys_clk);
        
        // ===========================
        // Test 3: All Zeros
        // ===========================
        $display("\nTest 3: Send All Zeros");
        
        repeat(5) @(posedge sys_clk);
        @(posedge sys_clk) i_tx_data = 8'h00;
        @(posedge sys_clk) i_tx_valid = 1'b1;
        @(posedge sys_clk) i_tx_valid = 1'b0;
        
        repeat(5) @(posedge sys_clk);
        @(posedge sys_clk) i_cs_n = 1'b0;
        repeat(10) @(posedge sys_clk);
        
        send_spi_byte(8'hFF);
        
        repeat(10) @(posedge sys_clk);
        @(posedge sys_clk) i_cs_n = 1'b1;
        
        repeat(20) @(posedge sys_clk);
        
        // ===========================
        // Test 4: All Ones
        // ===========================
        $display("\nTest 4: Send All Ones");
        
        repeat(5) @(posedge sys_clk);
        @(posedge sys_clk) i_tx_data = 8'hFF;
        @(posedge sys_clk) i_tx_valid = 1'b1;
        @(posedge sys_clk) i_tx_valid = 1'b0;
        
        repeat(5) @(posedge sys_clk);
        @(posedge sys_clk) i_cs_n = 1'b0;
        repeat(10) @(posedge sys_clk);
        
        send_spi_byte(8'h00);
        
        repeat(10) @(posedge sys_clk);
        @(posedge sys_clk) i_cs_n = 1'b1;
        
        repeat(20) @(posedge sys_clk);
        
        $display("\nAll tests completed!");
        $finish;
    end
    
    // =============================
    // Task: Send SPI Byte
    // =============================
    task send_spi_byte(input logic [7:0] byte_val);
        for (int i = 7; i >= 0; i--) begin
            // Set MOSI data bit
            @(posedge sys_clk) i_mosi = byte_val[i];
            
            // Wait for SCLK to complete a cycle
            @(posedge i_sclk);
            @(negedge i_sclk);
            
            // Small delay before next bit
            repeat(5) @(posedge sys_clk);
        end
    endtask
    
    // =============================
    // Monitors
    // =============================
    always @(posedge o_rx_valid) begin
        $display("  RX: Received 0x%02X at time %t", o_rx_data, $time);
    end
    
    always @(o_miso) begin
        $display("  MISO changed to: %b at time %t", o_miso, $time);
    end

endmodule

SPIQuadCopter/spiSlave/spi_slave_tb.vcd
$date
	Tue Dec  9 14:40:06 2025
$end
$version
	Icarus Verilog
$end
$timescale
	1ps
$end
$scope module spi_slave_tb $end
$var wire 1 ! o_rx_valid $end
$var wire 8 " o_rx_data [7:0] $end
$var wire 1 # o_miso $end
$var wire 1 $ o_busy $end
$var parameter 32 % DATA_WIDTH $end
$var parameter 32 & SPI_CLK_PERIOD $end
$var parameter 32 ' SYS_CLK_PERIOD $end
$var reg 1 ( i_cs_n $end
$var reg 1 ) i_mosi $end
$var reg 1 * i_sclk $end
$var reg 8 + i_tx_data [7:0] $end
$var reg 1 , i_tx_valid $end
$var reg 1 - rst_n $end
$var reg 1 . sys_clk $end
$scope module dut $end
$var wire 1 / cs_falling_edge $end
$var wire 1 . i_clk $end
$var wire 1 ( i_cs_n $end
$var wire 1 ) i_mosi $end
$var wire 1 - i_rst_n $end
$var wire 1 * i_sclk $end
$var wire 8 0 i_tx_data [7:0] $end
$var wire 1 , i_tx_valid $end
$var wire 1 1 sclk_falling_edge $end
$var wire 1 2 sclk_rising_edge $end
$var parameter 32 3 DATA_WIDTH $end
$var reg 3 4 bit_count [2:0] $end
$var reg 1 5 cs_n_r $end
$var reg 1 6 cs_n_sync1 $end
$var reg 1 7 cs_n_sync2 $end
$var reg 1 8 mosi_sync1 $end
$var reg 1 9 mosi_sync2 $end
$var reg 1 $ o_busy $end
$var reg 1 # o_miso $end
$var reg 8 : o_rx_data [7:0] $end
$var reg 1 ! o_rx_valid $end
$var reg 1 ; sclk_r1 $end
$var reg 1 < sclk_r2 $end
$var reg 1 = sclk_sync1 $end
$var reg 1 > sclk_sync2 $end
$var reg 8 ? shift_reg [7:0] $end
$var reg 8 @ tx_shift_reg [7:0] $end
$upscope $end
$scope task send_spi_byte $end
$var reg 8 A byte_val [7:0] $end
$scope begin $ivl_for_loop0 $end
$var integer 32 B i [31:0] $end
$upscope $end
$upscope $end
$upscope $end
$enddefinitions $end
$comment Show the parameter values. $end
$dumpall
b1000 3
b1010 '
b101000 &
b1000 %
$end
#0
$dumpvars
b0 B
bx A
b0 @
b0 ?
0>
0=
0<
0;
bx :
09
08
17
16
15
b0 4
02
01
b0 0
0/
0.
0-
0,
b0 +
0*
0)
1(
0$
0#
bx "
0!
$end
#5000
1.
#10000
0.
#15000
1.
#20000
0.
1*
#25000
1.
#30000
0.
#35000
1.
#40000
0.
0*
#45000
1.
#50000
0.
#55000
1.
#60000
0.
1*
#65000
1.
#70000
0.
#75000
1.
#80000
0.
0*
#85000
1.
#90000
0.
#95000
1-
1.
#100000
0.
1*
#105000
1=
1.
#110000
0.
#115000
1>
1.
#120000
0.
0*
#125000
12
1;
0=
1.
#130000
0.
#135000
02
0>
1<
1.
#140000
0.
1*
#145000
11
0;
1=
1.
#150000
0.
#155000
01
1>
0<
1.
#160000
0.
0*
#165000
12
1;
0=
1.
#170000
0.
#175000
02
0>
1<
1.
#180000
0.
1*
#185000
11
0;
1=
1.
#190000
0.
#195000
01
1>
0<
1.
#200000
0.
0*
#205000
12
1;
0=
b1011010 +
b1011010 0
1.
#210000
0.
#215000
02
0>
1<
b1011010 @
1,
1.
#220000
0.
1*
#225000
11
0;
1=
0,
1.
#230000
0.
#235000
01
1>
0<
1.
#240000
0.
0*
#245000
12
1;
0=
1.
#250000
0.
#255000
02
0>
1<
1.
#260000
0.
1*
#265000
11
0;
1=
1.
#270000
0.
#275000
01
1>
0<
1.
#280000
0.
0*
#285000
12
1;
06
0=
0(
1.
#290000
0.
#295000
1/
02
0>
07
1<
1.
#300000
0.
1*
#305000
0/
11
b0 @
1$
05
0;
1=
1.
#310000
0.
#315000
01
1>
0<
1.
#320000
0.
0*
#325000
12
1;
0=
1.
#330000
0.
#335000
02
0>
1<
b1 4
1.
#340000
0.
1*
#345000
11
0;
1=
1.
#350000
0.
#355000
01
1>
0<
1.
#360000
0.
0*
#365000
12
1;
0=
1.
#370000
0.
#375000
02
0>
1<
b10 4
1.
#380000
0.
1*
#385000
11
0;
1=
b111 B
b10100101 A
1.
#390000
0.
#395000
01
1>
18
0<
1)
1.
#400000
0.
0*
#405000
12
1;
19
0=
1.
#410000
0.
#415000
02
0>
1<
b11 4
b1 ?
1.
#420000
0.
1*
#425000
11
0;
1=
1.
#430000
0.
#435000
01
1>
0<
1.
#440000
0.
0*
#445000
12
1;
0=
1.
#450000
0.
#455000
02
0>
1<
b100 4
b11 ?
1.
#460000
0.
1*
#465000
11
0;
1=
1.
#470000
0.
#475000
01
1>
0<
1.
#480000
0.
0*
#485000
12
1;
0=
b110 B
1.
#490000
0.
#495000
02
0>
08
1<
b101 4
b111 ?
0)
1.
#500000
0.
1*
#505000
11
0;
09
1=
1.
#510000
0.
#515000
01
1>
0<
1.
#520000
0.
0*
#525000
12
1;
0=
1.
#530000
0.
#535000
02
0>
1<
b110 4
b1110 ?
1.
#540000
0.
1*
#545000
11
0;
1=
1.
#550000
0.
#555000
01
1>
0<
1.
#560000
0.
0*
#565000
12
1;
0=
b101 B
1.
#570000
0.
#575000
02
0>
18
1<
b111 4
b11100 ?
1)
1.
#580000
0.
1*
#585000
11
0;
19
1=
1.
#590000
0.
#595000
01
1>
0<
1.
#600000
0.
0*
#605000
12
1;
0=
1.
#610000
0.
#615000
02
0>
1<
1!
b111001 "
b111001 :
b0 4
b111001 ?
1.
#620000
0.
1*
#625000
11
0!
0;
1=
1.
#630000
0.
#635000
01
1>
0<
1.
#640000
0.
0*
#645000
12
1;
0=
b100 B
1.
#650000
0.
#655000
02
0>
08
1<
b1 4
b1110011 ?
0)
1.
#660000
0.
1*
#665000
11
0;
09
1=
1.
#670000
0.
#675000
01
1>
0<
1.
#680000
0.
0*
#685000
12
1;
0=
1.
#690000
0.
#695000
02
0>
1<
b10 4
b11100110 ?
1.
#700000
0.
1*
#705000
11
0;
1=
1.
#710000
0.
#715000
01
1>
0<
1.
#720000
0.
0*
#725000
12
1;
0=
b11 B
1.
#730000
0.
#735000
02
0>
1<
b11 4
b11001100 ?
1.
#740000
0.
1*
#745000
11
0;
1=
1.
#750000
0.
#755000
01
1>
0<
1.
#760000
0.
0*
#765000
12
1;
0=
1.
#770000
0.
#775000
02
0>
1<
b100 4
b10011000 ?
1.
#780000
0.
1*
#785000
11
0;
1=
1.
#790000
0.
#795000
01
1>
0<
1.
#800000
0.
0*
#805000
12
1;
0=
b10 B
1.
#810000
0.
#815000
02
0>
18
1<
b101 4
b110000 ?
1)
1.
#820000
0.
1*
#825000
11
0;
19
1=
1.
#830000
0.
#835000
01
1>
0<
1.
#840000
0.
0*
#845000
12
1;
0=
1.
#850000
0.
#855000
02
0>
1<
b110 4
b1100001 ?
1.
#860000
0.
1*
#865000
11
0;
1=
1.
#870000
0.
#875000
01
1>
0<
1.
#880000
0.
0*
#885000
12
1;
0=
b1 B
1.
#890000
0.
#895000
02
0>
08
1<
b111 4
b11000011 ?
0)
1.
#900000
0.
1*
#905000
11
0;
09
1=
1.
#910000
0.
#915000
01
1>
0<
1.
#920000
0.
0*
#925000
12
1;
0=
1.
#930000
0.
#935000
02
0>
1<
1!
b10000110 "
b10000110 :
b0 4
b10000110 ?
1.
#940000
0.
1*
#945000
11
0!
0;
1=
1.
#950000
0.
#955000
01
1>
0<
1.
#960000
0.
0*
#965000
12
1;
0=
b0 B
1.
#970000
0.
#975000
02
0>
18
1<
b1 4
b1100 ?
1)
1.
#980000
0.
1*
#985000
11
0;
19
1=
1.
#990000
0.
#995000
01
1>
0<
1.
#1000000
0.
0*
#1005000
12
1;
0=
1.
#1010000
0.
#1015000
02
0>
1<
b10 4
b11001 ?
1.
#1020000
0.
1*
#1025000
11
0;
1=
1.
#1030000
0.
#1035000
01
1>
0<
1.
#1040000
0.
0*
#1045000
12
1;
0=
b11111111111111111111111111111111 B
1.
#1050000
0.
#1055000
02
0>
1<
b11 4
b110011 ?
1.
#1060000
0.
1*
#1065000
11
0;
1=
1.
#1070000
0.
#1075000
01
1>
0<
1.
#1080000
0.
0*
#1085000
12
1;
0=
1.
#1090000
0.
#1095000
02
0>
1<
b100 4
b1100111 ?
1.
#1100000
0.
1*
#1105000
11
0;
1=
1.
#1110000
0.
#1115000
01
1>
0<
1.
#1120000
0.
0*
#1125000
12
1;
0=
1.
#1130000
0.
#1135000
02
0>
1<
b101 4
b11001111 ?
1.
#1140000
0.
1*
#1145000
11
0;
1=
1.
#1150000
0.
#1155000
01
1>
16
0<
1(
1.
#1160000
0.
0*
#1165000
12
1;
17
0=
1.
#1170000
0.
#1175000
02
0>
1<
15
0$
1.
