SerialWishbone/neoPXStrip/sendPx.v
`timescale 1ns / 1ns
//////////////////////////////////////////////////////////////////////////////////
// Company: 
// Engineer: 
// 
// Create Date: 07/26/2024 02:31:40 PM
// Design Name: 
// Module Name: sendPx
// Project Name: 
// Target Devices: 
// Tool Versions: 
// Description: 
// 
// Dependencies: 
// 
// Revision:
// Revision 0.01 - File Created
// Additional Comments:
// 
//////////////////////////////////////////////////////////////////////////////////


module sendPx(

    input wire axis_aclk,
    input wire axis_reset,
    
    /* AXIS slave */
    input wire [31:0] s_axis_data,
    input wire s_axis_valid,
    output wire s_axis_ready,
    
    /* output stream */
    output wire o_serial 
    );
    
/* 160_000_000 
.00625 us = 160_000_000 


     */ 
     
                        // WS2812B timings
localparam T0H_count =     16'd64,  // .4us 
           T1H_count =     16'd128,  // .8us
           T0L_count =     16'd136, // .85us
           T1L_count =     16'd72,  //  .45us
           GAP_count =     16'd15,
           RESET    =      16'd8800;// above 55us
    

/* SK6812
localparam T0H_count = 16'd48,  // .3us 
           T1H_count = 16'd96,  // .6us
           T0L_count = 16'd144, // .9us
           T1L_count = 16'd96,  // .6us
           GAP_count = 16'd10,
           RESET    =      16'd8800;// above 80us
 */
reg [7:0] state;
reg ready;
reg [15:0] counter;
reg [31:0] shift_reg;
reg out_bit;
reg [3:0] bit_state;
reg [15:0] gapTimer; 

localparam IDLE_BIT_BSTATE = 4'd0,
           WAIT_HIGH_BSTATE=4'd1,
           WAIT_LOW_BSTATE=4'd2,
           DONE_BIT_BSTATE=4'd3;
            
localparam IDLE_STATE = 8'd0,
          DONE_STATE = 8'd33,
          WAIT_STATE=8'd34;
          
initial begin
    ready = 0;
    state = IDLE_STATE;
    counter = 0;
    bit_state = IDLE_BIT_BSTATE;
    out_bit = 0;
 end            
 
always @(posedge axis_aclk) begin

    case ( state)
        DONE_STATE: begin
            $display("DONE_STATE ");
            bit_state <= IDLE_BIT_BSTATE;
            out_bit <= 1'b0;
            counter <= 0;
        end
        WAIT_STATE: begin
            $display("WAIT_STATE ");
            bit_state <= IDLE_BIT_BSTATE;
            out_bit <= 1'b0;
            counter <= 0;
        end

        IDLE_STATE: begin
            $display("IDLE_STATE ");
            bit_state <= IDLE_BIT_BSTATE;
            out_bit <= 1'b0;
            counter <= 0;
        end

        default: begin
             $display("DEFAULT ");
            case (bit_state)
                IDLE_BIT_BSTATE: begin
                    if (shift_reg[31] == 1)
                        counter <= T1H_count;
                    else 
                        counter <= T0H_count;
                    bit_state <= WAIT_HIGH_BSTATE;
                end
                WAIT_HIGH_BSTATE: begin     
                    $display("counter %d", counter);     
                    out_bit <= 1'b1;
                    counter <= counter - 1'b1;
                    if (counter == 0) begin
                        out_bit <= 1'b0;
                        bit_state <= WAIT_LOW_BSTATE;
                        if (shift_reg[31] == 1)
                            counter <= T1L_count;
                        else 
                            counter <= T0L_count;
                    end
                    else
                         out_bit <= 1'b1;
                end

                WAIT_LOW_BSTATE: begin
                    out_bit <= 1'b0;  
                    counter <= counter - 1'b1;
                    if (counter == 0) begin  
                        bit_state <= DONE_BIT_BSTATE;
                    end
                end

                DONE_BIT_BSTATE:  begin 
                    bit_state <= IDLE_BIT_BSTATE;
                    out_bit <= 1'b0;
                    counter <= 0;
                end
    
                default: begin 
                        bit_state <= IDLE_BIT_BSTATE;
                        out_bit <= 1'b0;
                        counter <= 0;
                end
            endcase 
        end


    endcase
  
 end  
                      
always @(posedge axis_aclk) begin
    
    if (axis_reset) begin
        state <= IDLE_STATE;
        ready <= 0;
        shift_reg <= 0;
        gapTimer <= 0;
    end
    else begin 

        case(state)
        IDLE_STATE: begin
            gapTimer <= 0;
            if ( s_axis_valid & ready) begin
                ready <= 0;
                shift_reg <= s_axis_data;
                state <= state + 1'b1;
            end
            else begin
                ready <= 1;
                state <= IDLE_STATE;
            end
        end    
        DONE_STATE: begin
            ready <= 1;
            gapTimer <= 0;
            state <= IDLE_STATE;
        end
        WAIT_STATE: begin
            ready <= 0;
            if(gapTimer== GAP_count)
                state <= IDLE_STATE;
            else
                gapTimer<= gapTimer + 1'b1;

        end
        default: begin
            ready <= 0;
            if( bit_state == DONE_BIT_BSTATE) begin
                shift_reg <= { shift_reg[30:0], 1'b0};
                state <= state +1;
            end
        end
        endcase
    end

end

assign s_axis_ready = ready;
assign o_serial = (bit_state!= IDLE_BIT_BSTATE)?out_bit:1'b0;

endmodule

SPIQuadCopter/neoPXStrip/tb_neopixels.v

`default_nettype none
`timescale 1 ns / 1 ns

module tb_neopixels();

    reg clk = 1;
    reg reset = 1;
    reg [31:0] ledData = 31'h0;
    reg axis_valid =0;
    wire o_neoserial;
    wire axis_is_ready;


sendPx dut(
    .axis_aclk(clk),
    .axis_reset(reset),
    .s_axis_data(ledData),
    .s_axis_valid(axis_valid),
    .s_axis_ready(axis_is_ready),
    .o_serial(o_neoserial)
    );

always begin
    #1 begin
        clk =!clk;
    end
end

always @( posedge clk) begin 
    if (reset) begin
    end
    else begin
        if (axis_is_ready && ~axis_valid) begin
            axis_valid <= 1;
            ledData <= ledData +1'b1;        
        end
        else begin
            if (axis_is_ready)
                axis_valid <= 0;
        end
    end
end


initial begin
    $dumpfile("tb_neopixels.vcd");
    $dumpvars(0,tb_neopixels);

    #10 reset<=1;
    #1 reset<=0;

    #100000 $finish;

end    



endmodule

SerialWishbone/neoPXStrip/tb_neopixels.vcd
$date
	Thu Nov 14 11:46:27 2024
$end
$version
	Icarus Verilog
$end
$timescale
	1ns
$end
$scope module tb_neopixels $end
$var wire 1 ! o_neoserial $end
$var wire 1 " axis_is_ready $end
$var reg 1 # axis_valid $end
$var reg 1 $ clk $end
$var reg 32 % ledData [31:0] $end
$var reg 1 & reset $end
$scope module dut $end
$var wire 1 $ axis_aclk $end
$var wire 1 & axis_reset $end
$var wire 32 ' s_axis_data [31:0] $end
$var wire 1 " s_axis_ready $end
$var wire 1 # s_axis_valid $end
$var wire 1 ! o_serial $end
$var reg 4 ( bit_state [3:0] $end
$var reg 16 ) counter [15:0] $end
$var reg 16 * gapTimer [15:0] $end
$var reg 1 + out_bit $end
$var reg 1 , ready $end
$var reg 32 - shift_reg [31:0] $end
$var reg 8 . state [7:0] $end
$upscope $end
$upscope $end
$enddefinitions $end
#0
$dumpvars
b0 .
bx -
0,
0+
bx *
b0 )
b0 (
b0 '
1&
b0 %
1$
0#
0"
0!
$end
#1
0$
#2
b0 *
b0 -
1$
#3
0$
#4
1$
#5
0$
#6
1$
#7
0$
#8
1$
#9
0$
#10
1$
#11
0&
0$
#12
1"
1,
1$
#13
0$
#14
b1 %
b1 '
1#
1$
#15
0$
#16
0#
b1 .
b1 -
0"
0,
1$
#17
0$
#18
b1 (
b1000000 )
1$
#19
0$
#20
1!
b111111 )
1+
1$
#21
0$
#22
b111110 )
1$
#23
0$
#24
b111101 )
1$
#25
0$
#26
b111100 )
1$
#27
0$
#28
b111011 )
1$
#29
0$
#30
b111010 )
1$
#31
0$
#32
b111001 )
1$
#33
0$
#34
b111000 )
1$
#35
0$
#36
b110111 )
1$
#37
0$
#38
b110110 )
1$
#39
0$
#40
b110101 )
1$
#41
0$
#42
b110100 )
1$
#43
0$
#44
b110011 )
1$
#45
0$
#46
b110010 )
1$
#47
0$
#48
b110001 )
1$
#49
0$
#50
b110000 )
1$
#51
0$
#52
b101111 )
1$
#53
0$
#54
b101110 )
1$
#55
0$
#56
b101101 )
1$
#57
0$
#58
b101100 )
1$
#59
0$
#60
b101011 )
1$
#61
0$
#62
b101010 )
1$
#63
0$
#64
b101001 )
1$
#65
0$
#66
b101000 )
1$
#67
0$
#68
b100111 )
1$
#69
0$
#70
b100110 )
1$
#71
0$
#72
b100101 )
1$
#73
0$
#74
b100100 )
1$
#75
0$
#76
b100011 )
1$
#77
0$
#78
b100010 )
1$
#79
0$
#80
b100001 )
1$
#81
0$
#82
b100000 )
1$
#83
0$
#84
b11111 )
1$
#85
0$
#86
b11110 )
1$
#87
0$
#88
b11101 )
1$
#89
0$
#90
b11100 )
1$
#91
0$
#92
b11011 )
1$
#93
0$
#94
b11010 )
1$
#95
0$
#96
b11001 )
1$
#97
0$
#98
b11000 )
1$
#99
0$
#100
b10111 )
1$
#101
0$
#102
b10110 )
1$
#103
0$
#104
b10101 )
1$
#105
0$
#106
b10100 )
1$
#107
0$
#108
b10011 )
1$
#109
0$
#110
b10010 )
1$
#111
0$
#112
b10001 )
1$
#113
0$
#114
b10000 )
1$
#115
0$
#116
b1111 )
1$
#117
0$
#118
b1110 )
1$
#119
0$
#120
b1101 )
1$
#121
0$
#122
b1100 )
1$
#123
0$
#124
b1011 )
1$
#125
0$
#126
b1010 )
1$
#127
0$
#128
b1001 )
1$
#129
0$
#130
b1000 )
1$
#131
0$
#132
b111 )
1$
#133
0$
#134
b110 )
1$
#135
0$
#136
b101 )
1$
#137
0$
#138
b100 )
1$
#139
0$
#140
b11 )
1$
#141
0$
#142
b10 )
1$
#143
0$
#144
b1 )
1$
#145
0$
#146
b0 )
1$
#147
0$
#148
0!
b10 (
0+
b10001000 )
1$
#149
0$
#150
b10000111 )
1$
#151
0$
#152
b10000110 )
1$
#153
0$
#154
b10000101 )
1$
#155
0$
#156
b10000100 )
1$
#157
0$
#158
b10000011 )
1$
#159
0$
#160
b10000010 )
1$
#161
0$
#162
b10000001 )
1$
#163
0$
#164
b10000000 )
1$
#165
0$
#166
b1111111 )
1$
#167
0$
#168
b1111110 )
1$
#169
0$
#170
b1111101 )
1$
#171
0$
#172
b1111100 )
1$
#173
0$
#174
b1111011 )
1$
#175
0$
#176
b1111010 )
1$
#177
0$
#178
b1111001 )
1$
#179
0$
#180
b1111000 )
1$
#181
0$
#182
b1110111 )
1$
#183
0$
#184
b1110110 )
1$
#185
0$
#186
b1110101 )
1$
#187
0$
#188
b1110100 )
1$
#189
0$
#190
b1110011 )
1$
#191
0$
#192
b1110010 )
1$
#193
0$
#194
b1110001 )
1$
#195
0$
#196
b1110000 )
1$
#197
0$
#198
b1101111 )
1$
#199
0$
#200
b1101110 )
1$
#201
0$
#202
b1101101 )
1$
#203
0$
#204
b1101100 )
1$
#205
0$
#206
b1101011 )
1$
#207
0$
#208
b1101010 )
1$
#209
0$
#210
b1101001 )
1$
#211
0$
#212
b1101000 )
1$
#213
0$
#214
b1100111 )
1$
#215
0$
#216
b1100110 )
1$
#217
0$
#218
b1100101 )
1$
#219
0$
#220
b1100100 )
1$
#221
0$
#222
b1100011 )
1$
#223
0$
#224
b1100010 )
1$
#225
0$
#226
b1100001 )
1$
#227
0$
#228
b1100000 )
1$
#229
0$
#230
b1011111 )
1$
#231
0$
#232
b1011110 )
1$
#233
0$
#234
b1011101 )
1$
#235
0$
#236
b1011100 )
1$
#237
0$
#238
b1011011 )
1$
#239
0$
#240
b1011010 )
1$
#241
0$
#242
b1011001 )
1$
#243
0$
#244
b1011000 )
1$
#245
0$
#246
b1010111 )
1$
#247
0$
#248
b1010110 )
1$
#249
0$
#250
b1010101 )
1$
#251
0$
#252
b1010100 )
1$
#253
0$
#254
b1010011 )
1$
#255
0$
#256
b1010010 )
1$
#257
0$
#258
b1010001 )
1$
#259
0$
#260
b1010000 )
1$
#261
0$
#262
b1001111 )
1$
#263
0$
#264
b1001110 )
1$
#265
0$
#266
b1001101 )
1$
#267
0$
#268
b1001100 )
1$
#269
0$
#270
b1001011 )
1$
#271
0$
#272
b1001010 )
1$
#273
0$
#274
b1001001 )
1$
#275
0$
#276
b1001000 )
1$
#277
0$
#278
b1000111 )
1$
#279
0$
#280
b1000110 )
1$
#281
0$
#282
b1000101 )
1$
#283
0$
#284
b1000100 )
1$
#285
0$
#286
b1000011 )
1$
#287
0$
#288
b1000010 )
1$
#289
0$
#290
b1000001 )
1$
#291
0$
#292
b1000000 )
1$
#293
0$
#294
b111111 )
1$
#295
0$
#296
b111110 )
1$
#297
0$
#298
b111101 )
1$
#299
0$
#300
b111100 )
1$
#301
0$
#302
b111011 )
1$
#303
0$
#304
b111010 )
1$
#305
0$
#306
b111001 )
1$
#307
0$
#308
b111000 )
1$
#309
0$
#310
b110111 )
1$
#311
0$
#312
b110110 )
1$
#313
0$
#314
b110101 )
1$
#315
0$
#316
b110100 )
1$
#317
0$
#318
b110011 )
1$
#319
0$
#320
b110010 )
1$
#321
0$
#322
b110001 )
1$
#323
0$
#324
b110000 )
1$
#325
0$
#326
b101111 )
1$
#327
0$
#328
b101110 )
1$
#329
0$
#330
b101101 )
1$
#331
0$
#332
b101100 )
1$
#333
0$
#334
b101011 )
1$
#335
0$
#336
b101010 )
1$
#337
0$
#338
b101001 )
1$
#339
0$
#340
b101000 )
1$
#341
0$
#342
b100111 )
1$
#343
0$
#344
b100110 )
1$
#345
0$
#346
b100101 )
1$
#347
0$
#348
b100100 )
1$
#349
0$
#350
b100011 )
1$
#351
0$
#352
b100010 )
1$
#353
0$
#354
b100001 )
1$
#355
0$
#356
b100000 )
1$
#357
0$
#358
b11111 )
1$
#359
0$
#360
b11110 )
1$
#361
0$
#362
b11101 )
1$
#363
0$
#364
b11100 )
1$
#365
0$
#366
b11011 )
1$
#367
0$
#368
b11010 )
1$
#369
0$
#370
b11001 )
1$
#371
0$
#372
b11000 )
1$
#373
0$
#374
b10111 )
1$
#375
0$
#376
b10110 )
1$
#377
0$
#378
b10101 )
1$
#379
0$
#380
b10100 )
1$
#381
0$
#382
b10011 )
1$
#383
0$
#384
b10010 )
1$
#385
0$
#386
b10001 )
1$
#387
0$
#388
b10000 )
1$
#389
0$
#390
b1111 )
1$
#391
0$
#392
b1110 )
1$
#393
0$
#394
b1101 )
1$
#395
0$
#396
b1100 )
1$
#397
0$
#398
b1011 )
1$
#399
0$
#400
b1010 )
1$
#401
0$
#402
b1001 )
1$
#403
0$
#404
b1000 )
1$
#405
0$
#406
b111 )
1$
#407
0$
#408
b110 )
1$
#409
0$
#410
b101 )
1$
#411
0$
#412
b100 )
1$
#413
0$
#414
b11 )
1$
#415
0$
#416
b10 )
1$
#417
0$
#418
b1 )
1$
#419
0$
#420
b0 )
1$
#421
0$
#422
b11 (
b1111111111111111 )
1$
#423
0$
#424
b10 .
b10 -
b0 )
b0 (
1$
#425
0$
#426
b1 (
b1000000 )
1$
#427
0$
#428
1!
b111111 )
1+
1$
#429
0$
#430
b111110 )
1$
#431
0$
#432
b111101 )
1$
#433
0$
#434
b111100 )
1$
#435
0$
#436
b111011 )
1$
#437
0$
#438
b111010 )
1$
#439
0$
#440
b111001 )
1$
#441
0$
#442
b111000 )
1$
#443
0$
#444
b110111 )
1$
#445
0$
#446
b110110 )
1$
#447
0$
#448
b110101 )
1$
#449
0$
#450
b110100 )
1$
#451
0$
#452
b110011 )
1$
#453
0$
#454
b110010 )
1$
#455
0$
#456
b110001 )
1$
#457
0$
#458
b110000 )
1$
#459
0$
#460
b101111 )
1$
#461
0$
#462
b101110 )
1$
#463
0$
#464
b101101 )
1$
#465
0$
#466
b101100 )
1$
#467
0$
#468
b101011 )
1$
#469
0$
#470
b101010 )
1$
#471
0$
#472
b101001 )
1$
#473
0$
#474
b101000 )
1$
#475
0$
#476
b100111 )
1$
#477
0$
#478
b100110 )
1$
#479
0$
#480
b100101 )
1$
#481
0$
#482
b100100 )
1$
#483
0$
#484
b100011 )
1$
#485
0$
#486
b100010 )
1$
#487
0$
#488
b100001 )
1$
#489
0$
#490
b100000 )
1$
#491
0$
#492
b11111 )
1$
#493
0$
#494
b11110 )
1$
#495
0$
#496
b11101 )
1$
#497
0$
#498
b11100 )
1$
#499
0$
#500
b11011 )
1$
#501
0$
#502
b11010 )
1$
#503
0$
#504
b11001 )
1$
#505
0$
#506
b11000 )
1$
#507
0$
#508
b10111 )
1$
#509
0$
#510
b10110 )
1$
#511
0$
#512
b10101 )
1$
#513
0$
#514
b10100 )
1$
#515
0$
#516
b10011 )
1$
#517
0$
#518
b10010 )
1$
#519
0$
#520
b10001 )
1$
#521
0$
#522
b10000 )
1$
#523
0$
#524
b1111 )
1$
#525
0$
#526
b1110 )
1$
#527
0$
#528
b1101 )
1$
#529
0$
#530
b1100 )
1$
#531
0$
#532
b1011 )
1$
#533
0$
#534
b1010 )
1$
#535
0$
#536
b1001 )
1$
#537
0$
#538
b1000 )
1$
#539
0$
#540
b111 )
1$
#541
0$
#542
b110 )
1$
#543
0$
#544
b101 )
1$
#545
0$
#546
b100 )
1$
#547
0$
#548
b11 )
1$
#549
0$
#550
b10 )
1$
#551
0$
#552
b1 )
1$
#553
0$
#554
b0 )
1$
#555
0$
#556
0!
b10 (
0+
b10001000 )
1$
#557
0$
#558
b10000111 )
1$
#559
0$
#560
b10000110 )
1$
#561
0$
#562
b10000101 )
1$
#563
0$
#564
b10000100 )
1$
#565
0$
#566
b10000011 )
1$
#567
0$
#568
b10000010 )
1$
#569
0$
#570
b10000001 )
1$
#571
0$
#572
b10000000 )
1$
#573
0$
#574
b1111111 )
1$
#575
0$
#576
b1111110 )
1$
#577
0$
#578
b1111101 )
1$
#579
0$
#580
b1111100 )
1$
#581
0$
#582
b1111011 )
1$
#583
0$
#584
b1111010 )
1$
#585
0$
#586
b1111001 )
1$
#587
0$
#588
b1111000 )
1$
#589
0$
#590
b1110111 )
1$
#591
0$
#592
b1110110 )
1$
#593
0$
#594
b1110101 )
1$
#595
0$
#596
b1110100 )
1$
#597
0$
#598
b1110011 )
1$
#599
0$
#600
b1110010 )
1$
#601
0$
#602
b1110001 )
1$
#603
0$
#604
b1110000 )
1$
#605
0$
#606
b1101111 )
1$
#607
0$
#608
b1101110 )
1$
#609
0$
#610
b1101101 )
1$
#611
0$
#612
b1101100 )
1$
#613
0$
#614
b1101011 )
1$
#615
0$
#616
b1101010 )
1$
#617
0$
#618
b1101001 )
1$
#619
0$
#620
b1101000 )
1$
#621
0$
#622
b1100111 )
1$
#623
0$
#624
b1100110 )
1$
#625
0$
#626
b1100101 )
1$
#627
0$
#628
b1100100 )
1$
#629
0$
#630
b1100011 )
1$
#631
0$
#632
b1100010 )
1$
#633
0$
#634
b1100001 )
1$
#635
0$
#636
b1100000 )
1$
#637
0$
#638
b1011111 )
1$
#639
0$
#640
b1011110 )
1$
#641
0$
#642
b1011101 )
1$
#643
0$
#644
b1011100 )
1$
#645
0$
#646
b1011011 )
1$
#647
0$
#648
b1011010 )
1$
#649
0$
#650
b1011001 )
1$
#651
0$
#652
b1011000 )
1$
#653
0$
#654
b1010111 )
1$
#655
0$
#656
b1010110 )
1$
#657
0$
#658
b1010101 )
1$
#659
0$
#660
b1010100 )
1$
#661
0$
#662
b1010011 )
1$
#663
0$
#664
b1010010 )
1$
#665
0$
#666
b1010001 )
1$
#667
0$
#668
b1010000 )
1$
#669
0$
#670
b1001111 )
1$
#671
0$
#672
b1001110 )
1$
#673
0$
#674
b1001101 )
1$
#675
0$
#676
b1001100 )
1$
#677
0$
#678
b1001011 )
1$
#679
0$
#680
b1001010 )
1$
#681
0$
#682
b1001001 )
1$
#683
0$
#684
b1001000 )
1$
#685
0$
#686
b1000111 )
1$
#687
0$
#688
b1000110 )
1$
#689
0$
#690
b1000101 )
1$
#691
0$
#692
b1000100 )
1$
#693
0$
#694
b1000011 )
1$
#695
0$
#696
b1000010 )
1$
#697
0$
#698
b1000001 )
1$
#699
0$
#700
b1000000 )
1$
#701
0$
#702
b111111 )
1$
#703
0$
#704
b111110 )
1$
#705
0$
#706
b111101 )
1$
#707
0$
#708
b111100 )
1$
#709
0$
#710
b111011 )
1$
#711
0$
#712
b111010 )
1$
#713
0$
#714
b111001 )
1$
#715
0$
#716
b111000 )
1$
#717
0$
#718
b110111 )
1$
#719
0$
#720
b110110 )
1$
#721
0$
#722
b110101 )
1$
#723
0$
#724
b110100 )
1$
#725
0$
#726
b110011 )
1$
#727
0$
#728
b110010 )
1$
#729
0$
#730
b110001 )
1$
#731
0$
#732
b110000 )
1$
#733
0$
#734
b101111 )
1$
#735
0$
#736
b101110 )
1$
#737
0$
#738
b101101 )
1$
#739
0$
#740
b101100 )
1$
#741
0$
#742
b101011 )
1$
#743
0$
#744
b101010 )
1$
#745
0$
#746
b101001 )
1$
#747
0$
#748
b101000 )
1$
#749
0$
#750
b100111 )
1$
#751
0$
#752
b100110 )
1$
#753
0$
#754
b100101 )
1$
#755
0$
#756
b100100 )
1$
#757
0$
#758
b100011 )
1$
#759
0$
#760
b100010 )
1$
#761
0$
#762
b100001 )
1$
#763
0$
#764
b100000 )
1$
#765
0$
#766
b11111 )
1$
#767
0$
#768
b11110 )
1$
#769
0$
#770
b11101 )
1$
#771
0$
#772
b11100 )
1$
#773
0$
#774
b11011 )
1$
#775
0$
#776
b11010 )
1$
#777
0$
#778
b11001 )
1$
#779
0$
#780
b11000 )
1$
#781
0$
#782
b10111 )
1$
#783
0$
#784
b10110 )
1$
#785
0$
#786
b10101 )
1$
#787
0$
#788
b10100 )
1$
#789
0$
#790
b10011 )
1$
#791
0$
#792
b10010 )
1$
#793
0$
#794
b10001 )
1$
#795
0$
#796
b10000 )
1$
#797
0$
#798
b1111 )
1$
#799
0$
#800
b1110 )
1$
#801
0$
#802
b1101 )
1$
#803
0$
#804
b1100 )
1$
#805
0$
#806
b1011 )
1$
#807
0$
#808
b1010 )
1$
#809
0$
#810
b1001 )
1$
#811
0$
#812
b1000 )
1$
#813
0$
#814
b111 )
1$
#815
0$
#816
b110 )
1$
#817
0$
#818
b101 )
1$
#819
0$
#820
b100 )
1$
#821
0$
#822
b11 )
1$
#823
0$
#824
b10 )
1$
#825
0$
#826
b1 )
1$
#827
0$
#828
b0 )
1$
#829
0$
#830
b11 (
b1111111111111111 )
1$
#831
0$
#832
b11 .
b100 -
b0 )
b0 (
1$
#833
0$
#834
b1 (
b1000000 )
1$
#835
0$
#836
1!
b111111 )
1+
1$
#837
0$
#838
b111110 )
1$
#839
0$
#840
b111101 )
1$
#841
0$
#842
b111100 )
1$
#843
0$
#844
b111011 )
1$
#845
0$
#846
b111010 )
1$
#847
0$
#848
b111001 )
1$
#849
0$
#850
b111000 )
1$
#851
0$
#852
b110111 )
1$
#853
0$
#854
b110110 )
1$
#855
0$
#856
b110101 )
1$
#857
0$
#858
b110100 )
1$
#859
0$
#860
b110011 )
1$
#861
0$
#862
b110010 )
1$
#863
0$
#864
b110001 )
1$
#865
0$
#866
b110000 )
1$
#867
0$
#868
b101111 )
1$
#869
0$
#870
b101110 )
1$
#871
0$
#872
b101101 )
1$
#873
0$
#874
b101100 )
1$
#875
0$
#876
b101011 )
1$
#877
0$
#878
b101010 )
1$
#879
0$
#880
b101001 )
1$
#881
0$
#882
b101000 )
1$
#883
0$
#884
b100111 )
1$
#885
0$
#886
b100110 )
1$
#887
0$
#888
b100101 )
1$
#889
0$
#890
b100100 )
1$
#891
0$
#892
b100011 )
1$
#893
0$
#894
b100010 )
1$
#895
0$
#896
b100001 )
1$
#897
0$
#898
b100000 )
1$
#899
0$
#900
b11111 )
1$
#901
0$
#902
b11110 )
1$
#903
0$
#904
b11101 )
1$
#905
0$
#906
b11100 )
1$
#907
0$
#908
b11011 )
1$
#909
0$
#910
b11010 )
1$
#911
0$
#912
b11001 )
1$
#913
0$
#914
b11000 )
1$
#915
0$
#916
b10111 )
1$
#917
0$
#918
b10110 )
1$
#919
0$
#920
b10101 )
1$
#921
0$
#922
b10100 )
1$
#923
0$
#924
b10011 )
1$
#925
0$
#926
b10010 )
1$
#927
0$
#928
b10001 )
1$
#929
0$
#930
b10000 )
1$
#931
0$
#932
b1111 )
1$
#933
0$
#934
b1110 )
1$
#935
0$
#936
b1101 )
1$
#937
0$
#938
b1100 )
1$
#939
0$
#940
b1011 )
1$
#941
0$
#942
b1010 )
1$
#943
0$
#944
b1001 )
1$
#945
0$
#946
b1000 )
1$
#947
0$
#948
b111 )
1$
#949
0$
#950
b110 )
1$
#951
0$
#952
b101 )
1$
#953
0$
#954
b100 )
1$
#955
0$
#956
b11 )
1$
#957
0$
#958
b10 )
1$
#959
0$
#960
b1 )
1$
#961
0$
#962
b0 )
1$
#963
0$
#964
0!
b10 (
0+
b10001000 )
1$
#965
0$
#966
b10000111 )
1$
#967
0$
#968
b10000110 )
1$
#969
0$
#970
b10000101 )
1$
#971
0$
#972
b10000100 )
1$
#973
0$
#974
b10000011 )
1$
#975
0$
#976
b10000010 )
1$
#977
0$
#978
b10000001 )
1$
#979
0$
#980
b10000000 )
1$
#981
0$
#982
b1111111 )
1$
#983
0$
#984
b1111110 )
1$
#985
0$
#986
b1111101 )
1$
#987
0$
#988
b1111100 )
1$
#989
0$
#990
b1111011 )
1$
#991
0$
#992
b1111010 )
1$
#993
0$
#994
b1111001 )
1$
#995
0$
#996
b1111000 )
1$
#997
0$
#998
b1110111 )
1$
#999
0$
#1000
b1110110 )
1$
#1001
0$
#1002
b1110101 )
1$
#1003
0$
#1004
b1110100 )
1$
#1005
0$
#1006
b1110011 )
1$
#1007
0$
#1008
b1110010 )
1$
#1009
0$
#1010
b1110001 )
1$
#1011
0$
#1012
b1110000 )
1$
#1013
0$
#1014
b1101111 )
1$
#1015
0$
#1016
b1101110 )
1$
#1017
0$
#1018
b1101101 )
1$
#1019
0$
#1020
b1101100 )
1$
#1021
0$
#1022
b1101011 )
1$
#1023
0$
#1024
b1101010 )
1$
#1025
0$
#1026
b1101001 )
1$
#1027
0$
#1028
b1101000 )
1$
#1029
0$
#1030
b1100111 )
1$
#1031
0$
#1032
b1100110 )
1$
#1033
0$
#1034
b1100101 )
1$
#1035
0$
#1036
b1100100 )
1$
#1037
0$
#1038
b1100011 )
1$
#1039
0$
#1040
b1100010 )
1$
#1041
0$
#1042
b1100001 )
1$
#1043
0$
#1044
b1100000 )
1$
#1045
0$
#1046
b1011111 )
1$
#1047
0$
#1048
b1011110 )
1$
#1049
0$
#1050
b1011101 )
1$
#1051
0$
#1052
b1011100 )
1$
#1053
0$
#1054
b1011011 )
1$
#1055
0$
#1056
b1011010 )
1$
#1057
0$
#1058
b1011001 )
1$
#1059
0$
#1060
b1011000 )
1$
#1061
0$
#1062
b1010111 )
1$
#1063
0$
#1064
b1010110 )
1$
#1065
0$
#1066
b1010101 )
1$
#1067
0$
#1068
b1010100 )
1$
#1069
0$
#1070
b1010011 )
1$
#1071
0$
#1072
b1010010 )
1$
#1073
0$
#1074
b1010001 )
1$
#1075
0$
#1076
b1010000 )
1$
#1077
0$
#1078
b1001111 )
1$
#1079
0$
#1080
b1001110 )
1$
#1081
0$
#1082
b1001101 )
1$
#1083
0$
#1084
b1001100 )
1$
#1085
0$
#1086
b1001011 )
1$
#1087
0$
#1088
b1001010 )
1$
#1089
0$
#1090
b1001001 )
1$
#1091
0$
#1092
b1001000 )
1$
#1093
0$
#1094
b1000111 )
1$
#1095
0$
#1096
b1000110 )
1$
#1097
0$
#1098
b1000101 )
1$
#1099
0$
#1100
b1000100 )
1$
#1101
0$
#1102
b1000011 )
1$
#1103
0$
#1104
b1000010 )
1$
#1105
0$
#1106
b1000001 )
1$
#1107
0$
#1108
b1000000 )
1$
#1109
0$
#1110
b111111 )
1$
#1111
0$
#1112
b111110 )
1$
#1113
0$
#1114
b111101 )
1$
#1115
0$
#1116
b111100 )
1$
#1117
0$
#1118
b111011 )
1$
#1119
0$
#1120
b111010 )
1$
#1121
0$
#1122
b111001 )
1$
#1123
0$
#1124
b111000 )
1$
#1125
0$
#1126
b110111 )
1$
#1127
0$
#1128
b110110 )
1$
#1129
0$
#1130
b110101 )
1$
#1131
0$
#1132
b110100 )
1$
#1133
0$
#1134
b110011 )
1$
#1135
0$
#1136
b110010 )
1$
#1137
0$
#1138
b110001 )
1$
#1139
0$
#1140
b110000 )
1$
#1141
0$
#1142
b101111 )
1$
#1143
0$
#1144
b101110 )
1$
#1145
0$
#1146
b101101 )
1$
#1147
0$
#1148
b101100 )
1$
#1149
0$
#1150
b101011 )
1$
#1151
0$
#1152
b101010 )
1$
#1153
0$
#1154
b101001 )
1$
#1155
0$
#1156
b101000 )
1$
#1157
0$
#1158
b100111 )
1$
#1159
0$
#1160
b100110 )
1$
#1161
0$
#1162
b100101 )
1$
#1163
0$
#1164
b100100 )
1$
#1165
0$
#1166
b100011 )
1$
#1167
0$
#1168
b100010 )
1$
#1169
0$
#1170
b100001 )
1$
#1171
0$
#1172
b100000 )
1$
#1173
0$
#1174
b11111 )
1$
#1175
0$
#1176
b11110 )
1$
#1177
0$
#1178
b11101 )
1$
#1179
0$
#1180
b11100 )
1$
#1181
0$
#1182
b11011 )
1$
#1183
0$
#1184
b11010 )
1$
#1185
0$
#1186
b11001 )
1$
#1187
0$
#1188
b11000 )
1$
#1189
0$
#1190
b10111 )
1$
#1191
0$
#1192
b10110 )
1$
#1193
0$
#1194
b10101 )
1$
#1195
0$
#1196
b10100 )
1$
#1197
0$
#1198
b10011 )
1$
#1199
0$
#1200
b10010 )
1$
#1201
0$
#1202
b10001 )
1$
#1203
0$
#1204
b10000 )
1$
#1205
0$
#1206
b1111 )
1$
#1207
0$
#1208
b1110 )
1$
#1209
0$
#1210
b1101 )
1$
#1211
0$
#1212
b1100 )
1$
#1213
0$
#1214
b1011 )
1$
#1215
0$
#1216
b1010 )
1$
#1217
0$
#1218
b1001 )
1$
#1219
0$
#1220
b1000 )
1$
#1221
0$
#1222
b111 )
1$
#1223
0$
#1224
b110 )
1$
#1225
0$
#1226
b101 )
1$
#1227
0$
#1228
b100 )
1$
#1229
0$
#1230
b11 )
1$
#1231
0$
#1232
b10 )
1$
#1233
0$
#1234
b1 )
1$
#1235
0$
#1236
b0 )
1$
#1237
0$
#1238
b11 (
b1111111111111111 )
1$
#1239
0$
#1240
b100 .
b1000 -
b0 )
b0 (
1$
#1241
0$
#1242
b1 (
b1000000 )
1$
#1243
0$
#1244
1!
b111111 )
1+
1$
#1245
0$
#1246
b111110 )
1$
